pyircsdk/__about__.py
pyircsdk/__init__.py
pyircsdk/command.py
pyircsdk/message.py
pyircsdk/pyircsdk.py
pyircsdk/event/__init__.py
pyircsdk/event/event.py
pyircsdk-1.7.2.dist-info/METADATA
pyircsdk-1.7.2.dist-info/WHEEL
pyircsdk-1.7.2.dist-info/licenses/LICENSE
pyircsdk-1.7.2.dist-info/RECORD
