Metadata-Version: 2.4
Name: pyircsdk
Version: 1.7.2
Summary: pyIRCSDK is a Python library for creating IRC bots and clients. It is designed to provide granular access to raw mesages and to provide an event emitter like interface for handling messages.
Project-URL: Homepage, https://github.com/bludot/pyircsdk
Project-URL: Issues, https://github.com/bludot/pyircsdk/issues
Author-email: Bludot <admin@floretos.com>
License-File: LICENSE
Classifier: License :: OSI Approved :: MIT License
Classifier: Operating System :: OS Independent
Classifier: Programming Language :: Python :: 3
Requires-Python: >=3.8
